{"version":"1.0.0","schema":"\"\"\"\nInstruction for establishing a live connection that is updated once the underlying data changes.\n\"\"\"\ndirective @cars_live(\n  \"Whether the query should be live or not.\"\n  if: Boolean = true\n  \"Propose a desired throttle interval ot the server in order to receive updates to at most once per \\\"throttle\\\" milliseconds. The server must not accept this value.\"\n  throttle: Int\n) on QUERY\n\ntype cars_Car {\n  driverId: Int!\n  id: ID!\n  name: String!\n}\n\ntype Query {\n  cars_carsByDriver(driverId: Int!): [cars_Car!]!\n}\n\ntype Subscription {\n  cars_carsByDriverSubscription(driverId: Int!): [cars_Car!]!\n}","dataSources":[{"Kind":2,"RootNodes":[{"typeName":"Query","fieldNames":["cars_carsByDriver"]},{"typeName":"Subscription","fieldNames":["cars_carsByDriverSubscription"]}],"ChildNodes":[{"typeName":"cars_Car","fieldNames":["driverId","id","name"]}],"Custom":{"Fetch":{"url":{"kind":0,"environmentVariableDefaultValue":"","environmentVariableName":"","placeholderVariableName":"","staticVariableContent":"http://localhost:4001/graphql"},"baseUrl":{"kind":0,"environmentVariableDefaultValue":"","environmentVariableName":"","placeholderVariableName":"","staticVariableContent":""},"path":{"kind":0,"environmentVariableDefaultValue":"","environmentVariableName":"","placeholderVariableName":"","staticVariableContent":""},"method":1,"body":{"kind":0,"environmentVariableDefaultValue":"","environmentVariableName":"","placeholderVariableName":"","staticVariableContent":""},"header":{},"query":[],"urlEncodeBody":false},"Subscription":{"Enabled":true,"URL":{"kind":0,"environmentVariableDefaultValue":"","environmentVariableName":"","placeholderVariableName":"","staticVariableContent":"http://localhost:4001/graphql"},"UseSSE":true},"Federation":{"Enabled":false,"ServiceSDL":""},"UpstreamSchema":"\"\"\"\nInstruction for establishing a live connection that is updated once the underlying data changes.\n\"\"\"\ndirective @live(\n  \"Whether the query should be live or not.\"\n  if: Boolean = true\n  \"Propose a desired throttle interval ot the server in order to receive updates to at most once per \\\"throttle\\\" milliseconds. The server must not accept this value.\"\n  throttle: Int\n) on QUERY\n\ntype Car {\n  driverId: Int!\n  id: ID!\n  name: String!\n}\n\ntype Query {\n  carsByDriver(driverId: Int!): [Car!]!\n}\n\ntype Subscription {\n  carsByDriverSubscription(driverId: Int!): [Car!]!\n}","HooksConfiguration":{"onWSTransportConnectionInit":false},"CustomScalarTypeFields":[]},"Directives":[{"directiveName":"cars_live","renameTo":"live"}],"RequestTimeoutSeconds":0}],"fields":[{"typeName":"Query","fieldName":"cars_carsByDriver","argumentsConfiguration":[{"name":"driverId","sourceType":1,"sourcePath":[],"renderConfiguration":0}],"disableDefaultFieldMapping":false,"path":["carsByDriver"],"requiresFields":[],"unescapeResponseJson":false},{"typeName":"Subscription","fieldName":"cars_carsByDriverSubscription","argumentsConfiguration":[{"name":"driverId","sourceType":1,"sourcePath":[],"renderConfiguration":0}],"disableDefaultFieldMapping":false,"path":["carsByDriverSubscription"],"requiresFields":[],"unescapeResponseJson":false}],"types":[{"typeName":"cars_Car","renameTo":"Car"}],"interpolateVariableDefinitionAsJSON":[]}